liaison/__init__.py
liaison/decorators.py
liaison/exceptions.py
liaison/namespace.py
liaison/schema.py
liaison-0.3.dist-info/LICENSE.txt
liaison-0.3.dist-info/METADATA
liaison-0.3.dist-info/WHEEL
liaison-0.3.dist-info/top_level.txt
liaison-0.3.dist-info/RECORD
