Metadata-Version: 2.1
Name: liaison
Version: 0.3
Summary: Liaison is a Python library for defining schemas, parsing and validating payloads
Home-page: https://github.com/Julian-Nash/liaison
Author: Julian Nash
License: UNKNOWN
Project-URL: Bug Tracker, https://github.com/Julian-Nash/liaison
Project-URL: Documentation, https://github.com/Julian-Nash/liaison
Project-URL: Source Code, https://github.com/Julian-Nash/liaison
Keywords: python schema parser
Platform: UNKNOWN
Classifier: Intended Audience :: Developers
Classifier: License :: OSI Approved :: MIT License
Classifier: Programming Language :: Python :: 3.6
Classifier: Programming Language :: Python :: 3.7
Classifier: Programming Language :: Python :: 3.8
Classifier: Programming Language :: Python :: 3.9
Classifier: Programming Language :: Python :: 3.10
License-File: LICENSE.txt
Provides-Extra: dev
Requires-Dist: pytest ; extra == 'dev'
Requires-Dist: black ; extra == 'dev'
Requires-Dist: coverage ; extra == 'dev'
Provides-Extra: test
Requires-Dist: pytest ; extra == 'test'
Requires-Dist: coverage ; extra == 'test'
